strangeworks_rigetti/__init__.py
strangeworks_rigetti/qc.py
strangeworks_rigetti/result.py
strangeworks_rigetti/strange.py
strangeworks_rigetti/upload_input_file.py
strangeworks_rigetti/utils.py
strangeworks_rigetti-0.2.23.dist-info/METADATA
strangeworks_rigetti-0.2.23.dist-info/WHEEL
strangeworks_rigetti-0.2.23.dist-info/licenses/LICENSE
strangeworks_rigetti-0.2.23.dist-info/RECORD
