Metadata-Version: 2.4
Name: strangeworks-rigetti
Version: 0.2.23
Summary: Strangeworks Rigetti SDK extension
License: Apache-2.0
License-File: LICENSE
Author: Strange Devs
Author-email: hello@strangeworks.com
Requires-Python: >=3.11,<4.00
Classifier: License :: OSI Approved :: Apache Software License
Classifier: Programming Language :: Python :: 3
Classifier: Programming Language :: Python :: 3.11
Classifier: Programming Language :: Python :: 3.12
Classifier: Programming Language :: Python :: 3.13
Classifier: Programming Language :: Python :: 3.14
Requires-Dist: matplotlib (>=3.10.3,<4.0.0)
Requires-Dist: numpy (>=2.2.5,<3.0.0)
Requires-Dist: pillow (>=11.2.1,<12.0.0)
Requires-Dist: pymupdf (>=1.25.5,<2.0.0)
Requires-Dist: pyquil (>=4.16.2,<5.0.0)
Requires-Dist: python-dotenv (>=1.1.0,<2.0.0)
Requires-Dist: qcs_api_client (>=0.26.5,<0.27.0)
Requires-Dist: strangeworks (>=0.7.6,<0.8.0)
